<?xml version="1.0" encoding="UTF-8"?>
<!DOCTYPE mapper 
PUBLIC "-//mybatis.org//DTD Mapper 3.0//EN" 
"http://mybatis.org/dtd/mybatis-3-mapper.dtd" >

<mapper namespace="org.joonzis.mybatis.mapper.employees"> 
	<select id="select_all" resultType="org.joonzis.vo.EmployeeVO">
		SELECT * FROM EMPLOYEES ORDER BY EMPLOYEE_ID
	</select>
	
	<select id="select_dept" parameterType="int" resultType="org.joonzis.vo.EmployeeVO">
		SELECT * FROM EMPLOYEES WHERE Department_id = #{deptId}
	</select>	
	

	
	<select id="select_dynamic" parameterType="map" resultType="org.joonzis.vo.EmployeeVO">	
		SELECT * FROM EMPLOYEES WHERE 	
		<choose>
			<when test="key==1">employee_id = #{value}</when>
			<when test="key==2">First_name = #{value}</when>
			<when test="key==3">Department_id = #{value}</when>
		</choose>	
	</select>
	 	
</mapper>





